motor_driver/__init__.py
motor_driver/dephy.py
motor_driver-0.1.0.dist-info/METADATA
motor_driver-0.1.0.dist-info/WHEEL
motor_driver-0.1.0.dist-info/RECORD
