Metadata-Version: 2.1
Name: motor-driver
Version: 0.1.0
Summary: This is a test package for the FlexSEA motor driver
Author: Senthur
Author-email: imsenthur@gmail.com
Requires-Python: >=3.11,<4.0
Classifier: Programming Language :: Python :: 3
Classifier: Programming Language :: Python :: 3.11
Requires-Dist: flexsea (>=12.0.3,<13.0.0)
Requires-Dist: numpy (>=1.26.4,<2.0.0)
